{
  "Status": {
    "CorrelationId": "d3056b1bb9d84775ad269abfa09cfa77",
    "Code": 200
  },
  "Payload": {
    "Trace": [],
    "ItemNumber": "2GPROC",
    "ItemDescription": "2 Ghz Processor",
    "NoteIndex": 333.0,
    "ItemShortName": "",
    "ItemType": "SalesInventory",
    "ItemGenericDescription": "",
    "StandardCost": 0.0,
    "CurrentCost": 250.0,
    "ItemShippingWeight": 0.0,
    "DecimalPlacesQTYS": "NotUsed",
    "DecimalPlacesCurrency": "One",
    "ItemTaxScheduleID": "",
    "TaxOptions": "Nontaxable",
    "IVIVIndex": 18,
    "IVIVOffsetIndex": 18,
    "IVCOGSIndex": 137,
    "IVSalesIndex": 112,
    "IVSalesDiscountsIndex": 128,
    "IVSalesReturnsIndex": 134,
    "IVInUseIndex": 0,
    "IVInServiceIndex": 141,
    "IVDamagedIndex": 141,
    "IVVariancesIndex": 783,
    "DropShipIndex": 445,
    "PurchasePriceVarianceIndex": 446,
    "UnrealizedPurchasePriceVarianceIndex": 446,
    "InventoryReturnsIndex": 450,
    "AssemblyVarianceIndex": 0,
    "ItemClassCode": "RM-ACT",
    "ItemTrackingOption": 1,
    "LotType": "",
    "KeepPeriodHistory": true,
    "KeepTrxHistory": true,
    "KeepCalendarHistory": true,
    "KeepDistributionHistory": true,
    "AllowBackOrders": true,
    "ValuationMethod": "FIFOPerpetual",
    "UOfMSchedule": "EACH",
    "AlternateItem1": "",
    "AlternateItem2": "",
    "MasterRecordType": 1,
    "ModifiedDate": "2017-05-21T00:00:00",
    "CreatedDate": "2017-05-21T00:00:00",
    "WarrantyDays": 0,
    "PriceLevel": "",
    "LocationCode": "",
    "PurchInflationIndex": 0,
    "PurchMonetaryCorrectionIndex": 0,
    "InventoryInflationIndex": 0,
    "InventoryMonetaryCorrectionIndex": 0,
    "COGSInflationIndex": 0,
    "COGSMonetaryCorrectionIndex": 0,
    "ItemCode": "",
    "TaxCommodityCode": "",
    "PriceGroup": "BUY",
    "PriceMethod": "CurrencyAmount",
    "PurchasingUOfM": "",
    "SellingUOfM": "",
    "KitCOGSAccountSource": "FromComponentItem",
    "LastGeneratedSerialNumber": "",
    "ABCCode": "B",
    "RevalueInventory": true,
    "TolerancePercentage": 0.0,
    "PurchaseItemTaxScheduleID": "",
    "PurchaseTaxOptions": "NonTaxable",
    "ItemPlanningType": "Normal",
    "StatisticalValuePercentage": 0.0,
    "CountryOrigin": "",
    "Inactive": false,
    "MinShelfLife1": 0,
    "MinShelfLife2": 0,
    "IncludeinDemandPlanning": false,
    "LotExpireWarning": true,
    "LotExpireWarningDays": 0,
    "LastGeneratedLotNumber": "",
    "LotSplitQuantity": 0.0,
    "UseQtyOverageTolerance": false,
    "UseQtyShortageTolerance": false,
    "QtyOverageTolerancePercentage": 0.0,
    "QtyShortageTolerancePercentage": 0.0,
    "IVSTDCostRevaluationIndex": 0,
    "UserCategoryValues1": "",
    "UserCategoryValues2": "",
    "UserCategoryValues3": "",
    "UserCategoryValues4": "",
    "UserCategoryValues5": "",
    "UserCategoryValues6": ""
  }
}